timple/__init__.py
timple/core.py
timple/patches.py
timple/timedelta.py
timple-0.1.8.dist-info/LICENSE.rst
timple-0.1.8.dist-info/METADATA
timple-0.1.8.dist-info/WHEEL
timple-0.1.8.dist-info/top_level.txt
timple-0.1.8.dist-info/RECORD
