Metadata-Version: 2.1
Name: timple
Version: 0.1.8
Summary: Extended functionality for plotting timedelta-like values with Matplotlib
Home-page: https://github.com/theOehrly/Timple
Author: Oehrly
Author-email: oehrly@mailbox.org
License: MIT
Platform: UNKNOWN
Requires-Python: >=3.7
